[
    {"date_":"2023-11-26-10","side_1_M":274845,"side_1_F":135249,"side_2_M":26935,"side_2_F":0,"Count":3176,"approx_count_side_1_M":87.0,"approx_count_side_1_F":43.0,"approx_count_side_2_M":8.0,"approx_count_side_2_F":0.0},
    {"date_":"2023-11-26-12","side_1_M":89765,"side_1_F":43972,"side_2_M":8741,"side_2_F":0,"Count":1363,"approx_count_side_1_M":66.0,"approx_count_side_1_F":32.0,"approx_count_side_2_M":6.0,"approx_count_side_2_F":0.0},
    {"date_":"2023-11-26-13","side_1_M":1465933,"side_1_F":729898,"side_2_M":145888,"side_2_F":0,"Count":4353,"approx_count_side_1_M":337.0,"approx_count_side_1_F":168.0,"approx_count_side_2_M":34.0,"approx_count_side_2_F":0.0}
]